LICENSE
README.md
pyproject.toml
setup.py
monotonic_align/__init__.py
monotonic_align/core.c
monotonic_align/core1alt.c
monotonic_align/core2.c
monotonic_align/core2eps.c
monotonic_align/mas.py
resemble_monotonic_align.egg-info/PKG-INFO
resemble_monotonic_align.egg-info/SOURCES.txt
resemble_monotonic_align.egg-info/dependency_links.txt
resemble_monotonic_align.egg-info/requires.txt
resemble_monotonic_align.egg-info/top_level.txt
tests/test_max_path.py