Metadata-Version: 2.1
Name: resemble-monotonic-align
Version: 1.2.1
License-File: LICENSE
Requires-Dist: numpy
